pdf_extraction/__init__.py
pdf_extraction/__main__.py
pdf_extraction/pdf_extractor.py
pdf_extraction/server.py
mseep_pdf_extraction-0.1.4.dist-info/METADATA
mseep_pdf_extraction-0.1.4.dist-info/WHEEL
mseep_pdf_extraction-0.1.4.dist-info/entry_points.txt
mseep_pdf_extraction-0.1.4.dist-info/top_level.txt
mseep_pdf_extraction-0.1.4.dist-info/RECORD
