Metadata-Version: 2.4
Name: mseep-pdf-extraction
Version: 0.1.4
Summary: MCP server to extract contents from PDF files
Author-email: mseep <support@skydeck.ai>
Requires-Python: >=3.11
Requires-Dist: mcp>=1.2.0
Requires-Dist: pypdf2>=3.0.1
Requires-Dist: pytesseract>=0.3.10
Requires-Dist: Pillow>=10.0.0
Requires-Dist: pydantic<3.0.0,>=2.10.1
Requires-Dist: pymupdf>=1.24.0
